odoo/addons/fs_file/README.rst
odoo/addons/fs_file/__init__.py
odoo/addons/fs_file/__manifest__.py
odoo/addons/fs_file/fields.py
odoo/addons/fs_file/i18n/es.po
odoo/addons/fs_file/i18n/fs_file.pot
odoo/addons/fs_file/i18n/it.po
odoo/addons/fs_file/readme/CONTRIBUTORS.md
odoo/addons/fs_file/readme/DESCRIPTION.md
odoo/addons/fs_file/readme/HISTORY.md
odoo/addons/fs_file/readme/USAGE.md
odoo/addons/fs_file/readme/newsfragments/.gitignore
odoo/addons/fs_file/static/description/icon.png
odoo/addons/fs_file/static/description/index.html
odoo/addons/fs_file/static/src/scss/fsfile_field.scss
odoo/addons/fs_file/static/src/views/fields/fsfile_field.esm.js
odoo/addons/fs_file/static/src/views/fields/fsfile_field.xml
odoo/addons/fs_file/tests/__init__.py
odoo/addons/fs_file/tests/models.py
odoo/addons/fs_file/tests/test_fs_file.py
odoo_addon_fs_file-18.0.1.0.0.3.dist-info/METADATA
odoo_addon_fs_file-18.0.1.0.0.3.dist-info/WHEEL
odoo_addon_fs_file-18.0.1.0.0.3.dist-info/top_level.txt
odoo_addon_fs_file-18.0.1.0.0.3.dist-info/RECORD
