Metadata-Version: 2.1
Name: odoo-addon-fs_file
Version: 18.0.1.0.0.3
Requires-Python: >=3.10
Requires-Dist: odoo-addon-fs_attachment==18.0.*
Requires-Dist: odoo==18.0.*
Summary: Field to store files into filesystem storages
Home-page: https://github.com/OCA/storage
License: AGPL-3
Author: ACSONE SA/NV,Odoo Community Association (OCA)
Author-email: support@odoo-community.org
Classifier: Programming Language :: Python
Classifier: Framework :: Odoo
Classifier: Framework :: Odoo :: 18.0
Classifier: License :: OSI Approved :: GNU Affero General Public License v3
Classifier: Development Status :: 3 - Alpha
